excerpts/__init__.py
excerpts/command_line.py
excerpts/main.py
excerpts/op.py
excerpts/ui.py
excerpts-2.1.0.dist-info/DESCRIPTION.rst
excerpts-2.1.0.dist-info/METADATA
excerpts-2.1.0.dist-info/RECORD
excerpts-2.1.0.dist-info/WHEEL
excerpts-2.1.0.dist-info/entry_points.txt
excerpts-2.1.0.dist-info/metadata.json
excerpts-2.1.0.dist-info/top_level.txt
