Metadata-Version: 2.0
Name: excerpts
Version: 2.1.0
Summary: Excerpt Markdown Style Comments From a File
Home-page: https://gitlab.com/fvafrcu/excerpts
Author: Andreas Dominik Cullmann
Author-email: fvafrcu@mailbox.org
License: BSD
Keywords: table of contents,structure comments
Platform: UNKNOWN
Classifier: Development Status :: 5 - Production/Stable
Classifier: Intended Audience :: Science/Research
Classifier: Topic :: Documentation
Classifier: License :: OSI Approved :: BSD License
Classifier: Programming Language :: Python :: 3
Classifier: Programming Language :: Python :: 3.4
Classifier: Operating System :: OS Independent
Provides-Extra: test
Provides-Extra: test
Requires-Dist: coverage; extra == 'test'
